hshmeng/__init__.py
hshmeng/hshmeng.py
hshmeng/yjl.py
hshmeng/dazi/__init__.py
hshmeng/dazi/dazi.py
hshmeng/help/__init__.py
hshmeng/help/help.py
hshmeng-2025.5.29.1.dist-info/licenses/LICENSE
hshmeng-2025.5.29.1.dist-info/METADATA
hshmeng-2025.5.29.1.dist-info/WHEEL
hshmeng-2025.5.29.1.dist-info/top_level.txt
hshmeng-2025.5.29.1.dist-info/RECORD
