Metadata-Version: 2.4
Name: hshmeng
Version: 2025.5.29.1
Summary: You hshmeng ZhiZuoDeZhongWenBianChengBao
Author: hshmeng
Author-email: hshmeng@foxmail.com
License: MIT
Requires-Python: >=3.8
License-File: LICENSE
Dynamic: author
Dynamic: author-email
Dynamic: description
Dynamic: description-content-type
Dynamic: license
Dynamic: license-file
Dynamic: requires-python
Dynamic: summary
